{"py/object": "rasa_core.featurizers.MaxHistoryTrackerFeaturizer", "max_history": 5, "remove_duplicates": true, "state_featurizer": {"py/object": "rasa_core.featurizers.BinarySingleStateFeaturizer", "input_state_map": {"entity_faculty": 7, "entity_form": 6, "entity_price": 5, "entity_time": 8, "intent_goodbye": 1, "intent_greet": 0, "intent_price": 3, "intent_request_info": 2, "intent_thankyou": 4, "prev_action_listen": 13, "prev_action_restart": 14, "prev_info_faculty": 24, "prev_show_price": 23, "prev_utter_ask_dosearch": 17, "prev_utter_ask_faculties": 18, "prev_utter_ask_form": 20, "prev_utter_ask_howcanhelp": 21, "prev_utter_ask_specialist": 19, "prev_utter_goodbye": 16, "prev_utter_greet": 15, "prev_utter_reply_thankyou": 22, "slot_faculty_0": 9, "slot_form_0": 10, "slot_price_0": 11, "slot_time_0": 12}, "num_features": 25, "slot_feature_len": 4, "user_feature_len": 9}, "use_intent_probabilities": false}